{
  "schema_version": 1,
  "dataset_tag": "macmpec",
  "tag": "Kaggle_MacMPEC_Ablation_NoPhaseI",
  "run_id": "20260430_015208",
  "problem_file": "pack-rig1p-32.nl.json",
  "status": "converged",
  "last_phase": "external_lpec_bstat_completed",
  "started_at": "2026-04-30T02:37:09.704538",
  "last_updated_at": "2026-04-30T02:46:21.941494",
  "elapsed_wall_s": 552.2369598,
  "artifacts": {
    "phase_ii_iteration_log_csv": "/kaggle/working/outputs_macmpec_ablation_no_phase_i/no-phase-i/iteration_logs/macmpec_Kaggle_MacMPEC_Ablation_NoPhaseI_20260430_015208_pack-rig1p-32.csv"
  },
  "stage_summaries": {
    "raw_run_mpecss": {
      "status": "converged",
      "stationarity": "B",
      "f_final": 0.8496890632342087,
      "comp_res": 9.99272812202652e-07,
      "kkt_res": 1.981203373850339e-08,
      "sign_test_pass": true,
      "b_stationarity": true,
      "lpec_obj": 0.0,
      "licq_holds": true,
      "n_outer_iters": 17,
      "n_restorations": 0,
      "cpu_time": 476.231459782,
      "log_count": 17,
      "point_sha256": "9a9e8e8ccf9aaea86459554e1e1241256567b0389fb958b1e07a9a9d03b46f03",
      "point_dim": 1855,
      "point_inf_norm": 0.8835856920589787,
      "point_l2_norm": 4.903037817309898,
      "point_all_finite": true,
      "bstat_details": {
        "lpec_status": "licq_equivalence",
        "classification": "B-stationary (S + LICQ)",
        "licq_holds": null,
        "licq_rank": 1639,
        "lpec_obj": null,
        "timed_out": null,
        "elapsed_s": null
      }
    },
    "after_external_bnlp": {
      "status": "converged",
      "stationarity": "B",
      "f_final": 0.8496890632342087,
      "comp_res": 9.99272812202652e-07,
      "kkt_res": 1.981203373850339e-08,
      "sign_test_pass": true,
      "b_stationarity": true,
      "lpec_obj": 0.0,
      "licq_holds": true,
      "n_outer_iters": 17,
      "n_restorations": 0,
      "cpu_time": 476.231459782,
      "log_count": 17,
      "point_sha256": "9a9e8e8ccf9aaea86459554e1e1241256567b0389fb958b1e07a9a9d03b46f03",
      "point_dim": 1855,
      "point_inf_norm": 0.8835856920589787,
      "point_l2_norm": 4.903037817309898,
      "point_all_finite": true,
      "bnlp_polish": {
        "accepted": false,
        "status": "Solve_Succeeded",
        "success": true,
        "f_val": 0.8535798207276457,
        "original_f_val": 0.8496890632342087,
        "comp_res_polish": 9.999993149517605e-09,
        "improvement": -0.003890757493437036
      },
      "bstat_details": {
        "lpec_status": "licq_equivalence",
        "classification": "B-stationary (S + LICQ)",
        "licq_holds": null,
        "licq_rank": 1639,
        "lpec_obj": null,
        "timed_out": null,
        "elapsed_s": null
      }
    },
    "final": {
      "status": "converged",
      "stationarity": "B",
      "f_final": 0.8496890632342087,
      "comp_res": 9.99272812202652e-07,
      "kkt_res": 1.981203373850339e-08,
      "sign_test_pass": true,
      "b_stationarity": true,
      "lpec_obj": 0.0,
      "licq_holds": true,
      "n_outer_iters": 17,
      "n_restorations": 0,
      "cpu_time": 476.231459782,
      "log_count": 17,
      "point_sha256": "9a9e8e8ccf9aaea86459554e1e1241256567b0389fb958b1e07a9a9d03b46f03",
      "point_dim": 1855,
      "point_inf_norm": 0.8835856920589787,
      "point_l2_norm": 4.903037817309898,
      "point_all_finite": true,
      "bnlp_polish": {
        "accepted": false,
        "status": "Solve_Succeeded",
        "success": true,
        "f_val": 0.8535798207276457,
        "original_f_val": 0.8496890632342087,
        "comp_res_polish": 9.999993149517605e-09,
        "improvement": -0.003890757493437036
      },
      "lpec_refine": {
        "bstat_found": true,
        "n_outer": 1,
        "n_inner_total": 1,
        "n_bnlps": 0,
        "n_lpecs": 1,
        "improvement": 0.0,
        "cpu_time": 61.17713239500017
      },
      "bstat_details": {
        "lpec_status": "complete",
        "classification": "B-stationary",
        "licq_holds": null,
        "licq_rank": 1639,
        "lpec_obj": 0.0,
        "timed_out": false,
        "elapsed_s": 54.34039878845215
      }
    }
  },
  "diagnostics": {
    "raw": {
      "point_sha256": "9a9e8e8ccf9aaea86459554e1e1241256567b0389fb958b1e07a9a9d03b46f03",
      "point_dim": 1855,
      "point_inf_norm": 0.8835856920589787,
      "point_l2_norm": 4.903037817309898,
      "point_all_finite": true,
      "all_finite": true,
      "objective_eval": 0.8496890632342087,
      "benchmark_feas_res": 9.99272812202652e-07,
      "biactive_res": 0.002056134315888511,
      "orig_constr_violation": 3.718125308506404e-12,
      "var_bound_violation": 9.999808408406308e-09,
      "comp_side_violation": 9.997423067169581e-09,
      "overall_primal_violation": 9.999808408406308e-09
    },
    "final": {
      "point_sha256": "9a9e8e8ccf9aaea86459554e1e1241256567b0389fb958b1e07a9a9d03b46f03",
      "point_dim": 1855,
      "point_inf_norm": 0.8835856920589787,
      "point_l2_norm": 4.903037817309898,
      "point_all_finite": true,
      "all_finite": true,
      "objective_eval": 0.8496890632342087,
      "benchmark_feas_res": 9.99272812202652e-07,
      "biactive_res": 0.002056134315888511,
      "orig_constr_violation": 3.718125308506404e-12,
      "var_bound_violation": 9.999808408406308e-09,
      "comp_side_violation": 9.997423067169581e-09,
      "overall_primal_violation": 9.999808408406308e-09
    }
  },
  "progress": {
    "seed": 42,
    "wall_timeout_cfg": 1800.0,
    "internal_timeout_s": 1440.0,
    "iteration": 17,
    "comp_res": 9.99272812202652e-07,
    "best_comp_res": 9.99272812202652e-07,
    "sign_pass": true,
    "solver_status": "Solve_Succeeded",
    "n_biactive": 378,
    "t_k": 1.5108032808398144e-06,
    "bnlp_accepted": false
  },
  "problem_name": "pack-rig1p-32",
  "problem_metadata": {
    "family": "macmpec",
    "n_x": 1855,
    "n_comp": 861,
    "n_con": 993,
    "n_p": 0,
    "source_path": "/kaggle/input/datasets/mrsaurabhtanwar/mpecss-benchmark/benchmarks/macmpec/macmpec-json/pack-rig1p-32.nl.json"
  },
  "completed_at": "2026-04-30T02:46:21.941369"
}