{
  "schema_version": 1,
  "dataset_tag": "mpeclib",
  "tag": "Kaggle_MPECLib",
  "run_id": "20260430_013023",
  "problem_file": "finda30l.nl.json",
  "status": "converged",
  "last_phase": "external_lpec_bstat_completed",
  "started_at": "2026-04-30T03:05:48.058934",
  "last_updated_at": "2026-04-30T03:53:49.332418",
  "elapsed_wall_s": 2881.273493173001,
  "artifacts": {
    "phase_ii_iteration_log_csv": "/kaggle/working/outputs/iteration_logs/mpeclib_Kaggle_MPECLib_20260430_013023_finda30l.csv"
  },
  "stage_summaries": {
    "raw_run_mpecss": {
      "status": "converged",
      "stationarity": "C",
      "f_final": 367.62033848920197,
      "comp_res": 6.816791720719225e-08,
      "kkt_res": null,
      "sign_test_pass": false,
      "b_stationarity": false,
      "lpec_obj": -26.0,
      "licq_holds": false,
      "n_outer_iters": 24,
      "n_restorations": 0,
      "cpu_time": 2728.3833946659997,
      "log_count": 24,
      "point_sha256": "f9e361afacbd0dfe3a91ba53723e4faacbf201a5b5152bf63419665f40d5eb10",
      "point_dim": 211,
      "point_inf_norm": 56.05953421698146,
      "point_l2_norm": 207.7732481076937,
      "point_all_finite": true,
      "phase_i": {
        "success": true,
        "cpu_time": 38.06443558299998,
        "n_attempts": 2,
        "initial_comp_res": 3.062363369909067,
        "final_comp_res": 6.816791720719225e-08,
        "feasibility_achieved": true,
        "near_feasibility": true
      },
      "bstat_details": {
        "lpec_status": "complete",
        "classification": "not B-stationary",
        "licq_holds": false,
        "licq_rank": 157,
        "lpec_obj": -26.0,
        "timed_out": false,
        "elapsed_s": 0.025513172149658203
      }
    },
    "after_external_bnlp": {
      "status": "converged",
      "stationarity": "C",
      "f_final": 367.62033848920197,
      "comp_res": 6.816791720719225e-08,
      "kkt_res": null,
      "sign_test_pass": false,
      "b_stationarity": false,
      "lpec_obj": -26.0,
      "licq_holds": false,
      "n_outer_iters": 24,
      "n_restorations": 0,
      "cpu_time": 2728.3833946659997,
      "log_count": 24,
      "point_sha256": "f9e361afacbd0dfe3a91ba53723e4faacbf201a5b5152bf63419665f40d5eb10",
      "point_dim": 211,
      "point_inf_norm": 56.05953421698146,
      "point_l2_norm": 207.7732481076937,
      "point_all_finite": true,
      "phase_i": {
        "success": true,
        "cpu_time": 38.06443558299998,
        "n_attempts": 2,
        "initial_comp_res": 3.062363369909067,
        "final_comp_res": 6.816791720719225e-08,
        "feasibility_achieved": true,
        "near_feasibility": true
      },
      "bnlp_polish": {
        "accepted": false,
        "status": "Maximum_Iterations_Exceeded",
        "success": false,
        "f_val": 217.5417889135754,
        "original_f_val": 367.62033848920197,
        "comp_res_polish": null,
        "improvement": 0
      },
      "bstat_details": {
        "lpec_status": "complete",
        "classification": "not B-stationary",
        "licq_holds": false,
        "licq_rank": 157,
        "lpec_obj": -26.0,
        "timed_out": false,
        "elapsed_s": 0.025513172149658203
      }
    },
    "final": {
      "status": "converged",
      "stationarity": "C",
      "f_final": 53.692724094880305,
      "comp_res": 7.050652766760907e-11,
      "kkt_res": 0.8965519939398732,
      "sign_test_pass": false,
      "b_stationarity": false,
      "lpec_obj": -5.0586242476440155,
      "licq_holds": false,
      "n_outer_iters": 24,
      "n_restorations": 0,
      "cpu_time": 2728.3833946659997,
      "log_count": 24,
      "point_sha256": "0d2c5ce7ac5b28a69e11aa214dc3812465d7a2808528518d719df0fed3f0d4ec",
      "point_dim": 211,
      "point_inf_norm": 1233.053213251003,
      "point_l2_norm": 1284.7910066062477,
      "point_all_finite": true,
      "phase_i": {
        "success": true,
        "cpu_time": 38.06443558299998,
        "n_attempts": 2,
        "initial_comp_res": 3.062363369909067,
        "final_comp_res": 6.816791720719225e-08,
        "feasibility_achieved": true,
        "near_feasibility": true
      },
      "bnlp_polish": {
        "accepted": false,
        "status": "Maximum_Iterations_Exceeded",
        "success": false,
        "f_val": 217.5417889135754,
        "original_f_val": 367.62033848920197,
        "comp_res_polish": null,
        "improvement": 0
      },
      "lpec_refine": {
        "bstat_found": false,
        "n_outer": 2,
        "n_inner_total": 3,
        "n_bnlps": 5,
        "n_lpecs": 3,
        "improvement": 313.92761439432167,
        "cpu_time": 120.35439873699943
      },
      "bstat_details": {
        "lpec_status": "complete",
        "classification": "not B-stationary",
        "licq_holds": null,
        "licq_rank": 160,
        "lpec_obj": -5.0586242476440155,
        "timed_out": false,
        "elapsed_s": 0.04928398132324219
      }
    }
  },
  "diagnostics": {
    "raw": {
      "point_sha256": "f9e361afacbd0dfe3a91ba53723e4faacbf201a5b5152bf63419665f40d5eb10",
      "point_dim": 211,
      "point_inf_norm": 56.05953421698146,
      "point_l2_norm": 207.7732481076937,
      "point_all_finite": true,
      "all_finite": true,
      "objective_eval": 367.62033848920197,
      "benchmark_feas_res": 6.816791720719225e-08,
      "biactive_res": 2.9042205543643214e-08,
      "orig_constr_violation": 1.1259020241489174e-14,
      "var_bound_violation": 0.0,
      "comp_side_violation": 1.1320572967448341e-10,
      "overall_primal_violation": 1.1320572967448341e-10
    },
    "final": {
      "point_sha256": "0d2c5ce7ac5b28a69e11aa214dc3812465d7a2808528518d719df0fed3f0d4ec",
      "point_dim": 211,
      "point_inf_norm": 1233.053213251003,
      "point_l2_norm": 1284.7910066062477,
      "point_all_finite": true,
      "all_finite": true,
      "objective_eval": 53.692724094880305,
      "benchmark_feas_res": 7.050652766760907e-11,
      "biactive_res": 1.966606970863048e-12,
      "orig_constr_violation": 8.671307227814395e-09,
      "var_bound_violation": 1.0694573627970221e-12,
      "comp_side_violation": 1.966606970863048e-12,
      "overall_primal_violation": 8.671307227814395e-09
    }
  },
  "progress": {
    "seed": 42,
    "wall_timeout_cfg": 3600.0,
    "internal_timeout_s": 2880.0,
    "iteration": 24,
    "comp_res": 6.816791720719225e-08,
    "best_comp_res": 7.050652766760907e-11,
    "feasibility_achieved": true,
    "sign_pass": false,
    "solver_status": "Solve_Succeeded",
    "n_biactive": 0,
    "t_k": 7.450580596923828e-09,
    "bnlp_accepted": false
  },
  "problem_name": "finda30l",
  "problem_metadata": {
    "family": "find_a",
    "n_x": 211,
    "n_comp": 100,
    "n_con": 128,
    "n_p": 0,
    "source_path": "/kaggle/input/datasets/mralexsantora/mpecss-benchmark/benchmarks/mpeclib/mpeclib-json/finda30l.nl.json"
  },
  "completed_at": "2026-04-30T03:53:49.332332"
}